{
  "date": "30 Jun 2026",
  "date_iso": "2026-06-30",
  "prev_high": 24035.55078125,
  "prev_low": 23851.94921875,
  "prev_close": 23931.900390625,
  "cpr_upper": 23943.8,
  "cpr_lower": 23935.9,
  "cpw": 7.9,
  "pivot": 23939.8,
  "r1": 24027.7,
  "r2": 24123.4,
  "s1": 23844.0,
  "s2": 23756.2,
  "call_strike": 24300,
  "put_strike": 23500,
  "regime": "Sideways",
  "persistence": 0.7551,
  "escape": 0.2449,
  "prob_up": 15,
  "prob_side": 80,
  "prob_down": 5,
  "vix": 13.470000267028809,
  "exp_high": 24135,
  "exp_low": 23729,
  "conf_overall": 46
}